CHANGELOG.md
LICENSE.txt
README.md
authcaptureproxy/__init__.py
authcaptureproxy/auth_capture_proxy.py
authcaptureproxy/cli.py
authcaptureproxy/const.py
authcaptureproxy/examples/__init__.py
authcaptureproxy/examples/modifiers.py
authcaptureproxy/examples/testers.py
authcaptureproxy/helper.py
authcaptureproxy/stackoverflow.py
authcaptureproxy-1.3.3.dist-info/LICENSE.txt
authcaptureproxy-1.3.3.dist-info/METADATA
authcaptureproxy-1.3.3.dist-info/WHEEL
authcaptureproxy-1.3.3.dist-info/entry_points.txt
authcaptureproxy-1.3.3.dist-info/RECORD
