Metadata-Version: 2.1
Name: authcaptureproxy
Version: 1.3.3
Summary: A Python project to create a proxy to capture authentication information from a webpage. This is useful to capture oauth login details without access to a third-party oauth.
Home-page: https://github.com/alandtse/auth_capture_proxy
License: Apache-2.0
Author: Alan D. Tse
Maintainer: Alan D. Tse
Requires-Python: >=3.10,<4.0
Classifier: Development Status :: 3 - Alpha
Classifier: Environment :: Console
Classifier: Intended Audience :: Developers
Classifier: License :: OSI Approved :: Apache Software License
Classifier: Natural Language :: English
Classifier: Operating System :: OS Independent
Classifier: Programming Language :: Python :: 3
Classifier: Programming Language :: Python :: 3.10
Classifier: Programming Language :: Python :: 3.11
Classifier: Programming Language :: Python :: 3.12
Classifier: Programming Language :: Python :: 3.13
Classifier: Programming Language :: Python :: 3 :: Only
Classifier: Programming Language :: Python :: 3.8
Classifier: Programming Language :: Python :: 3.9
Classifier: Topic :: Software Development :: Libraries :: Python Modules
Provides-Extra: all
Requires-Dist: aiohttp (>=3,<4)
Requires-Dist: beautifulsoup4 (>=4,<5)
Requires-Dist: httpx
Requires-Dist: multidict (>=6,<7)
Requires-Dist: typer (>=0.3,<1.0)
Requires-Dist: yarl (>=1,<2)
Project-URL: CI, https://github.com/alandtse/auth_capture_proxy/actions
Project-URL: Documentation, https://auth_capture_proxy.readthedocs.io
Project-URL: Download, https://pypi.org/project/authcaptureproxy/
Project-URL: Issues, https://github.com/alandtse/auth_capture_proxy/issues
Project-URL: Repository, https://github.com/alandtse/auth_capture_proxy
